nWin64Tls/__init__.py
nWin64Tls/nWin64Tls.py
nWin64Tls-0.0.1.dist-info/METADATA
nWin64Tls-0.0.1.dist-info/WHEEL
nWin64Tls-0.0.1.dist-info/top_level.txt
nWin64Tls-0.0.1.dist-info/RECORD
