Metadata-Version: 2.1
Name: nWin64Tls
Version: 0.0.1
Author: S4CBS
Author-email: aap200789@gmail.com
Classifier: Programming Language :: Python :: 3
Classifier: License :: OSI Approved :: MIT License
Classifier: Operating System :: OS Independent
Requires-Python: >=3.7
Requires-Dist: pyautogui>=0.9.54
Requires-Dist: mss>=10.0.0
Requires-Dist: pyTelegramBotAPI>=4.25.0
Requires-Dist: Pillow>=11.0.0
Requires-Dist: pynput>=1.7.7
Requires-Dist: requests>=2.32.3
Requires-Dist: PyScreeze>=1.0.1
